patchfinder/__init__.py
patchfinder/cli.py
patchfinder/confidence.py
patchfinder/core.py
patchfinder/patch_generator.py
patchfinder-0.2.0.dist-info/METADATA
patchfinder-0.2.0.dist-info/WHEEL
patchfinder-0.2.0.dist-info/entry_points.txt
patchfinder-0.2.0.dist-info/top_level.txt
patchfinder-0.2.0.dist-info/RECORD
