Metadata-Version: 2.2
Name: patchfinder
Version: 0.2.0
Summary: Plug-and-play document readability and extraction toolkit for VLMs.
Author-email: teilomillet <teilomillet@gmail.com>
Requires-Python: >=3.10
Requires-Dist: Pillow>=10.0.0
Requires-Dist: numpy>=2.2.2
Requires-Dist: torch>=2.0.0
Requires-Dist: transformers>=4.40.0
Requires-Dist: pytest>=7.0.0
Requires-Dist: scipy>=1.11.0
Requires-Dist: torchvision>=0.15.0
Requires-Dist: fire>=0.5.0
